code_navigation_python-0.0.3.dist-info/METADATA
code_navigation_python-0.0.3.dist-info/WHEEL
code_navigation_python-0.0.3.dist-info/licenses/LICENSE
code_navigation_python/__init__.py
code_navigation_python/code_navigation_python.abi3.so
code_navigation_python-0.0.3.dist-info/RECORD
