Metadata-Version: 2.3
Name: code_navigation_python
Version: 0.0.3
Classifier: Programming Language :: Rust
Classifier: Programming Language :: Python :: Implementation :: CPython
Classifier: Programming Language :: Python :: Implementation :: PyPy
License-File: LICENSE
Summary: A python package written in rust for code navigation features like text search, fuzzy search and go to definition/references
Author: 
License: Apache
Requires-Python: >=3.8
